irisml/tasks/create_llava_model/__init__.py
irisml/tasks/create_llava_model/create_llava_model.py
irisml/tasks/create_llava_model/model/LICENSE
irisml/tasks/create_llava_model/model/__init__.py
irisml/tasks/create_llava_model/model/apply_delta.py
irisml/tasks/create_llava_model/model/builder.py
irisml/tasks/create_llava_model/model/consolidate.py
irisml/tasks/create_llava_model/model/constants.py
irisml/tasks/create_llava_model/model/llava_arch.py
irisml/tasks/create_llava_model/model/make_delta.py
irisml/tasks/create_llava_model/model/mm_utils.py
irisml/tasks/create_llava_model/model/utils.py
irisml/tasks/create_llava_model/model/language_model/llava_llama.py
irisml/tasks/create_llava_model/model/language_model/llava_mistral.py
irisml/tasks/create_llava_model/model/language_model/llava_mpt.py
irisml/tasks/create_llava_model/model/multimodal_encoder/builder.py
irisml/tasks/create_llava_model/model/multimodal_encoder/clip_encoder.py
irisml/tasks/create_llava_model/model/multimodal_projector/builder.py
irisml_tasks_llava-0.0.6.dist-info/LICENSE
irisml_tasks_llava-0.0.6.dist-info/METADATA
irisml_tasks_llava-0.0.6.dist-info/WHEEL
irisml_tasks_llava-0.0.6.dist-info/top_level.txt
irisml_tasks_llava-0.0.6.dist-info/RECORD
