Metadata-Version: 2.1
Name: irisml-tasks-llava
Version: 0.0.6
Summary: Irisml adapter tasks for LLAVA models
Home-page: https://github.com/microsoft/irisml-tasks-llava
Author: irisdev
License: MIT
Requires-Python: >=3.8
License-File: LICENSE
Requires-Dist: irisml
Requires-Dist: accelerate
Requires-Dist: azure-identity
Requires-Dist: azure-storage-blob
Requires-Dist: bitsandbytes
Requires-Dist: einops
Requires-Dist: packaging
Requires-Dist: Pillow
Requires-Dist: sentencepiece
Requires-Dist: tokenizers >=0.13.3
Requires-Dist: transformers >=4.36.0
